answerbook_webhook_test/__init__.py
answerbook_webhook_test/app.py
answerbook_webhook_test-0.0.4.dist-info/METADATA
answerbook_webhook_test-0.0.4.dist-info/WHEEL
answerbook_webhook_test-0.0.4.dist-info/entry_points.txt
answerbook_webhook_test-0.0.4.dist-info/top_level.txt
answerbook_webhook_test-0.0.4.dist-info/RECORD
