Metadata-Version: 2.1
Name: answerbook-webhook-test
Version: 0.0.4
Summary: answerbook_webhook_test - Just a simple webhook test app
Home-page: https://github.com/jondkelley/answerbook_webhook_test
Author: Jonathan Kelley
Author-email: jonkelley@gmail.com
License: Copyleft
Platform: UNKNOWN
Requires-Dist: Click (==7.0)
Requires-Dist: Flask (==1.1.2)
Requires-Dist: Flask-Assets (==0.12)
Requires-Dist: Jinja2 (==2.11.2)
Requires-Dist: python-dateutil (==2.8.0)
Requires-Dist: logdna
